{
  "id": "gateway-service-planning-docs",
  "name": "gateway-service-planning-docs",
  "title": "brainstorm: gateway service planning docs",
  "description": "",
  "status": "completed",
  "dev_type": null,
  "scope": null,
  "package": null,
  "priority": "P2",
  "creator": "EmptyDust",
  "assignee": "EmptyDust",
  "createdAt": "2026-06-28",
  "completedAt": "2026-06-28",
  "branch": null,
  "base_branch": "chore/agent-commit-hook",
  "worktree_path": null,
  "commit": null,
  "pr_url": null,
  "subtasks": [],
  "children": [],
  "parent": null,
  "relatedFiles": [],
  "notes": "",
  "meta": {}
}